README.md
setup.py
TOPSIS_Gurman_101803472.egg-info/PKG-INFO
TOPSIS_Gurman_101803472.egg-info/SOURCES.txt
TOPSIS_Gurman_101803472.egg-info/dependency_links.txt
TOPSIS_Gurman_101803472.egg-info/entry_points.txt
TOPSIS_Gurman_101803472.egg-info/requires.txt
TOPSIS_Gurman_101803472.egg-info/top_level.txt
src/topsis.py