Metadata-Version: 2.1
Name: TOPSIS-Gurman-101803472
Version: 1.0.1
Summary: A Python package implementing TOPSIS technique.
Home-page: https://coe1316.ml
Author: Gurman Bhullar
Author-email: gbhullar_be18@thapar.edu
License: MIT
Platform: UNKNOWN
Classifier: License :: OSI Approved :: MIT License
Classifier: Programming Language :: Python :: 3
Classifier: Programming Language :: Python :: 3.4
Classifier: Programming Language :: Python :: 3.5
Classifier: Programming Language :: Python :: 3.6
Classifier: Programming Language :: Python :: 3.7
